{
    "msl":{
        "ck":{
            "reconstructed":{
                "kernels":["msl_ra_[a-z]{8}_v[0-9]{1}.bc$",
                           "msl_cruise_recon_raw[a-z]{2,3}_v[0-9]{1}.bc$",
                           "msl_edl_v[0-9]{2}.bc$",
                           "msl_surf_[a-z]{2,5}_tlm[a-z]{0,3}.bc$",
                           "msl_surf_[a-z]{2,5}_[a-z]{2,6}_[0-9]{4}_[0-9]{4}_v[0-9]{1}.bc$",
                           "msl_surf_[a-z]{2,5}_tlm[a-z]{0,3}_spanned.bc",
                           "msl_cruise_recon_nospin.bc$",
                           "msl_still_at_ls_v1.bc$",
                           "msl_surf_rover_runout.bc$",
                           "msl_rover2cacs_v[0-9]{1}.bc$",
                           "msl_rsm_calpose_v[0-9]{1}.bc$",
                           "msl_hga_zero_v[0-9]{1}.bc$"]
            }
        },
        "fk":{
            "kernels":["msl.tf(.history)?$",
                       "msl_v[0-9]{2}.tf$",
                       "msl_tp_gc[0-9]{6}_iau2000_v[0-9]{1}.tf",
                       "msl_tp_[a-z]{2,3}[0-9]{6}_iau2000_v[0-9]{1}.tf$"]
        },
        "sclk":{
            "kernels":["msl.tsc$",
                       "msl_lmst_[a-z]{2,3}[0-9]{6}_v[0-9]{1}.tsc$",
                       "MSL_[0-9]{2}_SCLKSCET.[0-9]{5}.tsc$"]
        },
        "ik":{
            "kernels":["msl_[a-z]{2,5}_[c,v][0-9]{2}.ti$",
                       "msl_struct_v[0-9]{2}.ti$",
                       "msl_[a-z]{2,3}_zero_v[0-9]{1}.ti$",
                       "msl_[a-z]{4,5}_[0-9]{8}_c[0-9]{2}.ti$",
                       "msl_m[l,r]{1}_[0-9]{8}_c[0-9]{2}.ti$",
                       "msl_[a-z]{3}_[0-9]{8}_c[0-9]{2}.ti$"]
        },
        "lsk":{
            "kernels":"msl.tls(.history)?$"
        },
        "spk":{
            "kernels":["msl_struct_v[0-9]{2}.bsp$",
                       "msl_cruise_v[0-9]{1}.bsp$",
                       "msl_edl_v[0-9]{2}.bsp$",
                       "msl_ls_ops[0-9]{6}_iau2000_v[0-9]{1}.bsp$",
                       "msl_surf_rover_[a-z]{0,3}_?(runout)?.bsp$",
                       "msl_surf_[a-z]{5}_[a-z]{3}_[0-9]{4}_[0-9]{4}_v[0-9]{1}.bsp",
                       "msl_atls_[a-z]{2,3}[0-9]{6}_v[0-9]{1}.bsp$",
                       "msl_cruise.bsp(.history)?$",
                       "msl_[a-z]{2}_gc[0-9]{6}_iau2000_v[0-9]{1}.bsp$",
                       "msl_still_at_ls_v[0-9]{1}.bsp$",
                       "msl_spk_cruise_od057_v[0-9]{1}-tcm2_eph-edl-landed.bsp$",
                       "msl_cruise_merged_[0-9]{6}.bsp"]
        }
    }
}